graphwork.pypy39-pp73-win_amd64.pyd
graphworkc.py
graphworkc-1.2.2.dist-info/METADATA
graphworkc-1.2.2.dist-info/WHEEL
graphworkc-1.2.2.dist-info/top_level.txt
graphworkc-1.2.2.dist-info/RECORD
